commit/__init__.py
commit/commits.py
commit/config.py
commit/main.py
commit/prompt.py
commit/py.typed
quick_commit-0.2.0.dist-info/licenses/LICENSE.txt
quick_commit-0.2.0.dist-info/METADATA
quick_commit-0.2.0.dist-info/WHEEL
quick_commit-0.2.0.dist-info/entry_points.txt
quick_commit-0.2.0.dist-info/top_level.txt
quick_commit-0.2.0.dist-info/RECORD
