Metadata-Version: 2.4
Name: quick-commit
Version: 0.2.0
Summary: Add your description here
Requires-Python: >=3.10
License-File: LICENSE.txt
Requires-Dist: appdirs>=1.4.4
Requires-Dist: gitpython>=3.1.44
Requires-Dist: pyyaml>=6.0.2
Provides-Extra: test
Requires-Dist: pytest>=7.2; extra == "test"
Provides-Extra: docs
Requires-Dist: furo>=2023.9.10; extra == "docs"
Requires-Dist: setuptools-scm>=8.1; extra == "docs"
Requires-Dist: sphinxcontrib-bibtex>=2.4.2; extra == "docs"
Requires-Dist: sphinx-copybutton>=0.5; extra == "docs"
Requires-Dist: ipykernel; extra == "docs"
Requires-Dist: nbsphinx; extra == "docs"
Requires-Dist: sphinxext-opengraph>=0.9; extra == "docs"
Requires-Dist: sphinx-autodoc-typehints; extra == "docs"
Dynamic: license-file
